HISTORY.rst
LICENSE
MANIFEST.in
README.rst
requirements.txt
setup.py
bin/prudentia
prudentia/Vagrantfile.j2
prudentia/__init__.py
prudentia/__init__.pyc
prudentia/ansible.cfg
prudentia/cli.py
prudentia/digital_ocean.py
prudentia/domain.py
prudentia/factory.py
prudentia/local.py
prudentia/simple.py
prudentia/ssh.py
prudentia/vagrant.py
prudentia.egg-info/PKG-INFO
prudentia.egg-info/SOURCES.txt
prudentia.egg-info/dependency_links.txt
prudentia.egg-info/requires.txt
prudentia.egg-info/top_level.txt
prudentia/__pycache__/__init__.cpython-35.pyc
prudentia/__pycache__/cli.cpython-35.pyc
prudentia/__pycache__/digital_ocean.cpython-35.pyc
prudentia/__pycache__/domain.cpython-35.pyc
prudentia/__pycache__/factory.cpython-35.pyc
prudentia/__pycache__/local.cpython-35.pyc
prudentia/__pycache__/simple.cpython-35.pyc
prudentia/__pycache__/ssh.cpython-35.pyc
prudentia/__pycache__/vagrant.cpython-35.pyc
prudentia/files/chrome/apt-source
prudentia/files/common/etc-update-motd-d-95-prudentia
prudentia/files/common/ucf.conf
prudentia/files/fail2ban/jail.local.j2
prudentia/files/jenkins/apt-source
prudentia/files/mailhog/mailhog.conf.j2
prudentia/files/mongodb/apt-source
prudentia/files/mongodb/apt-source-26
prudentia/files/mysql/my.cnf
prudentia/files/mysql_5.7/my.cnf
prudentia/files/opencv/apt-source
prudentia/files/protractor/webdriver-upstart.conf
prudentia/files/tor/apt-source
prudentia/files/vsftpd/vsftpd.conf
prudentia/inventories/aws_elb_instances.py
prudentia/plugins/action/hashi_vault.py
prudentia/plugins/lookup/hashi_vault.py
prudentia/tasks/add-sudo-user.yml
prudentia/tasks/add_known_hosts.yml
prudentia/tasks/chrome.yml
prudentia/tasks/collectd.yml
prudentia/tasks/common-setup.yml
prudentia/tasks/elasticsearch.yml
prudentia/tasks/fail2ban.yml
prudentia/tasks/fontforge.yml
prudentia/tasks/git.yml
prudentia/tasks/github.yml
prudentia/tasks/haproxy.yml
prudentia/tasks/java.yml
prudentia/tasks/java7.yml
prudentia/tasks/jenkins.yml
prudentia/tasks/jre.yml
prudentia/tasks/mailhog.yml
prudentia/tasks/mercurial.yml
prudentia/tasks/mongodb.yml
prudentia/tasks/mongodb_2.6.yml
prudentia/tasks/mongodb_3.yml
prudentia/tasks/monit.yml
