Metadata-Version: 1.0
Name: prudentia
Version: 2.6
Summary: Continuous Deployment toolkit.
Home-page: https://github.com/StarterSquad/prudentia
Author: Tiziano Perrucci
Author-email: tiziano@startersquad.com
License: MIT
Platform: Posix; MacOS X;
